palma_sdk/__init__.py
palma_sdk/auth.py
palma_sdk/client_http.py
palma_sdk/http_client.py
palma_sdk-0.1.1.dist-info/METADATA
palma_sdk-0.1.1.dist-info/WHEEL
palma_sdk-0.1.1.dist-info/RECORD
