Metadata-Version: 2.4
Name: palma-sdk
Version: 0.1.1
Summary: High-level Python SDK for the MCP Gateway: async context-managed HTTP client with optional OIDC tokens.
Author: Palma AI
Author-email: team@palma.ai
Requires-Python: >=3.10,<4.0
Classifier: Programming Language :: Python :: 3
Classifier: Programming Language :: Python :: 3.10
Classifier: Programming Language :: Python :: 3.11
Classifier: Programming Language :: Python :: 3.12
Classifier: Programming Language :: Python :: 3.13
Classifier: Programming Language :: Python :: 3.14
Requires-Dist: asyncio-mqtt (>=0.16.1,<0.17.0)
Requires-Dist: httpx (>=0.27.0,<0.28.0)
Requires-Dist: mcp (>=1.1.2,<2.0.0)
Requires-Dist: pydantic (>=2.5.0,<3.0.0)
Requires-Dist: typing-extensions (>=4.8.0,<5.0.0)
Requires-Dist: websockets (>=12.0,<13.0)
